odoo/addons/fieldservice_sale/README.rst
odoo/addons/fieldservice_sale/__init__.py
odoo/addons/fieldservice_sale/__manifest__.py
odoo/addons/fieldservice_sale/i18n/de.po
odoo/addons/fieldservice_sale/i18n/es.po
odoo/addons/fieldservice_sale/i18n/es_CL.po
odoo/addons/fieldservice_sale/i18n/fieldservice_sale.pot
odoo/addons/fieldservice_sale/i18n/it.po
odoo/addons/fieldservice_sale/i18n/pt_BR.po
odoo/addons/fieldservice_sale/migrations/12.0.2.0.0/pre-migration.py
odoo/addons/fieldservice_sale/models/__init__.py
odoo/addons/fieldservice_sale/models/fsm_branch.py
odoo/addons/fieldservice_sale/models/fsm_location.py
odoo/addons/fieldservice_sale/models/fsm_order.py
odoo/addons/fieldservice_sale/models/product_template.py
odoo/addons/fieldservice_sale/models/sale_order.py
odoo/addons/fieldservice_sale/models/sale_order_line.py
odoo/addons/fieldservice_sale/readme/CONFIGURE.rst
odoo/addons/fieldservice_sale/readme/CONTRIBUTORS.rst
odoo/addons/fieldservice_sale/readme/DESCRIPTION.rst
odoo/addons/fieldservice_sale/readme/INSTALL.rst
odoo/addons/fieldservice_sale/readme/ROADMAP.rst
odoo/addons/fieldservice_sale/readme/USAGE.rst
odoo/addons/fieldservice_sale/security/ir.model.access.csv
odoo/addons/fieldservice_sale/static/description/icon.png
odoo/addons/fieldservice_sale/static/description/index.html
odoo/addons/fieldservice_sale/static/description/description/icon.png
odoo/addons/fieldservice_sale/static/description/description/index.html
odoo/addons/fieldservice_sale/tests/__init__.py
odoo/addons/fieldservice_sale/tests/test_fsm_sale_common.py
odoo/addons/fieldservice_sale/tests/test_fsm_sale_onchange_partner.py
odoo/addons/fieldservice_sale/tests/test_fsm_sale_order.py
odoo/addons/fieldservice_sale/views/fsm_branch.xml
odoo/addons/fieldservice_sale/views/fsm_location.xml
odoo/addons/fieldservice_sale/views/fsm_order.xml
odoo/addons/fieldservice_sale/views/product_template.xml
odoo/addons/fieldservice_sale/views/res_config_settings.xml
odoo12_addon_fieldservice_sale-12.0.2.5.2.dist-info/METADATA
odoo12_addon_fieldservice_sale-12.0.2.5.2.dist-info/WHEEL
odoo12_addon_fieldservice_sale-12.0.2.5.2.dist-info/top_level.txt
odoo12_addon_fieldservice_sale-12.0.2.5.2.dist-info/RECORD
